sdic/__init__.py
sdic/constants.py
sdic/db/__init__.py
sdic/db/base.py
sdic/db/models.py
sdiccy-0.2.0.dist-info/METADATA
sdiccy-0.2.0.dist-info/WHEEL
sdiccy-0.2.0.dist-info/RECORD
