Metadata-Version: 2.3
Name: sdiccy
Version: 0.2.0
Summary: 
Author: gxl
Author-email: gaoxiaoliang123@126.com
Requires-Python: >=3.13
Classifier: Programming Language :: Python :: 3
Classifier: Programming Language :: Python :: 3.13
Requires-Dist: oracledb (>=3.2.0,<4.0.0)
Requires-Dist: pandas (>=2.3.1,<3.0.0)
Requires-Dist: sqlalchemy (>=2.0.41,<3.0.0)
